first_compare_mcp/__init__.py
first_compare_mcp-0.1.0.dist-info/WHEEL
first_compare_mcp-0.1.0.dist-info/entry_points.txt
first_compare_mcp-0.1.0.dist-info/METADATA
first_compare_mcp-0.1.0.dist-info/RECORD
