Metadata-Version: 2.3
Name: first-compare-mcp
Version: 0.1.0
Summary: Add your description here
Author: lizk7
Author-email: lizk7 <lizk7@lenovo.com>
Requires-Dist: mcp[cli]>=1.23.1
Requires-Python: >=3.13
